BSpyConvert/__init__.py
BSpyConvert/convert.py
BSpyConvert/exporter.py
BSpyConvert/importer.py
BSpyConvert-1.2.dist-info/LICENSE
BSpyConvert-1.2.dist-info/METADATA
BSpyConvert-1.2.dist-info/WHEEL
BSpyConvert-1.2.dist-info/top_level.txt
BSpyConvert-1.2.dist-info/RECORD
