Metadata-Version: 2.1
Name: BSpyConvert
Version: 1.2
Summary: Library for converting BSpy splines and solid models to and from OpenCascade (OCCT) equivalents and a variety of geometry and CAD file formats
Home-page: http://github.com/ericbrec/BSpyConvert
Author: Eric Brechner
Author-email: ericbrec@msn.com
License: MIT
Project-URL: Bug Tracker, http://github.com/ericbrec/BSpyConvert/issues
Keywords: bspline,B-spline,OCCT,OCC,OpenCascade,CAD,STEP,IGES,STL,solid modeling,solid model
Classifier: License :: OSI Approved :: MIT License
Classifier: Environment :: Win32 (MS Windows)
Classifier: Environment :: Console
Classifier: Intended Audience :: Developers
Classifier: Intended Audience :: Science/Research
Classifier: Topic :: Scientific/Engineering
Classifier: Topic :: Scientific/Engineering :: Mathematics
Classifier: Topic :: Software Development :: Libraries :: Python Modules
Classifier: Programming Language :: Python :: 3
Classifier: Operating System :: OS Independent
Requires-Python: >=3.0
License-File: LICENSE
Requires-Dist: numpy
Requires-Dist: scipy
Requires-Dist: PyOpenGL
Requires-Dist: pyopengltk
Requires-Dist: bspy
